easy_dwpose/__init__.py
easy_dwpose/body_estimation/__init__.py
easy_dwpose/body_estimation/detector.py
easy_dwpose/body_estimation/pose.py
easy_dwpose/body_estimation/utils.py
easy_dwpose/body_estimation/wholebody.py
easy_dwpose/draw/__init__.py
easy_dwpose/draw/mimic_motion.py
easy_dwpose/draw/musepose.py
easy_dwpose/draw/openpose.py
easy_dwpose/dwpose.py
easy_dwpose-1.0.2.dist-info/LICENSE
easy_dwpose-1.0.2.dist-info/METADATA
easy_dwpose-1.0.2.dist-info/WHEEL
easy_dwpose-1.0.2.dist-info/RECORD
