Metadata-Version: 2.1
Name: easy_dwpose
Version: 1.0.2
Summary: 
Requires-Python: >=3.9,<4.0
Classifier: Programming Language :: Python :: 3
Classifier: Programming Language :: Python :: 3.9
Classifier: Programming Language :: Python :: 3.10
Classifier: Programming Language :: Python :: 3.11
Classifier: Programming Language :: Python :: 3.12
Requires-Dist: huggingface_hub (>=0.24.6,<0.25.0)
Requires-Dist: imageio (>=2.9.0,<3.0.0)
Requires-Dist: loguru (>=0.7.2,<0.8.0)
Requires-Dist: matplotlib (>=3.9.2,<4.0.0)
Requires-Dist: numpy (>=1.26.4,<2.0.0)
Requires-Dist: omegaconf (==2.3.0)
Requires-Dist: onnxruntime (==1.16.2) ; sys_platform == "darwin"
Requires-Dist: onnxruntime-gpu (==1.16.2) ; sys_platform == "linux"
Requires-Dist: opencv-python (>=4.10.0.84,<5.0.0.0)
Requires-Dist: torch (>=2.2.2,<3.0.0)
Requires-Dist: tqdm (>=4.66.5,<5.0.0)
